[
    {
        "device_id": "b56676e2067a67c8",
        "key": "xDT21311",
        "expirydate": "25-11-2026",
        "Allowoffline": false
    },
    {
        "device_id": "24a6eb4508f6b4aa",
        "key": "xDT21399",
        "expirydate": "25-11-2026",
        "Allowoffline": false
    },
    {
        "device_id": "53686cc6602c835f",
        "key": "xDT21388",
        "expirydate": "21-11-2024",
        "Allowoffline": false
    },
    {
        "device_id": "1924cec9000c56ab",
        "key": "xDT213x7",
        "expirydate": "21-09-2026",
        "Allowoffline": false
    },
    {
        "device_id": "30eee29b",
        "key": "A2B2C3",
        "expirydate": "25-05-2025",
        "Allowoffline": true
    }
]
